dmsc/__init__.py
dmsc/dmsc.cpython-38-aarch64-linux-gnu.so
dmsc-0.1.5.dist-info/METADATA
dmsc-0.1.5.dist-info/WHEEL
dmsc-0.1.5.dist-info/licenses/LICENSE
dmsc-0.1.5.dist-info/RECORD
