Metadata-Version: 2.4
Name: dmsc
Version: 0.1.5
Classifier: Programming Language :: Rust
Classifier: Programming Language :: Python :: Implementation :: CPython
Classifier: Programming Language :: Python :: Implementation :: PyPy
Classifier: Programming Language :: Python :: 3.8
Classifier: Programming Language :: Python :: 3.9
Classifier: Programming Language :: Python :: 3.10
Classifier: Programming Language :: Python :: 3.11
Classifier: Programming Language :: Python :: 3.12
Classifier: Programming Language :: Python :: 3.13
Classifier: Programming Language :: Python :: 3.14
License-File: LICENSE
Summary: Dunimd Middleware Service - A high-performance Rust middleware framework with modular architecture
Keywords: middleware,rust,async,gateway,service-mesh
Author: Dunimd Team
Requires-Python: >=3.8
